{
    "Version": "1.2",
    "Data": {
        "Source": "c:\\projectdwarf\\projectdwarf\\plugins\\advancedsessions\\source\\advancedsessions\\private\\advancedsessions.cpp",
        "ProvidedModule": "",
        "PCH": "c:\\projectdwarf\\projectdwarf\\intermediate\\build\\win64\\x64\\projectcalypso\\development\\engine\\sharedpch.engine.project.valapi.cpp20.inclorderoldest.h.pch",
        "Includes": [
            "c:\\projectdwarf\\projectdwarf\\plugins\\advancedsessions\\intermediate\\build\\win64\\x64\\unrealgame\\development\\advancedsessions\\definitions.advancedsessions.h",
            "c:\\projectdwarf\\projectdwarf\\plugins\\advancedsessions\\source\\advancedsessions\\classes\\advancedsessions.h"
        ],
        "ImportedModules": [],
        "ImportedHeaderUnits": []
    }
}